kmeans1d-0.5.0.dist-info/RECORD
kmeans1d-0.5.0.dist-info/LICENSE
kmeans1d-0.5.0.dist-info/WHEEL
kmeans1d-0.5.0.dist-info/top_level.txt
kmeans1d-0.5.0.dist-info/METADATA
kmeans1d/__init__.py
kmeans1d/core.py
kmeans1d/version.txt
kmeans1d/_core.abi3.so
