Metadata-Version: 2.1
Name: kmeans1d
Version: 0.5.0
Summary: A Python package for optimal 1D k-means clustering
Home-page: https://github.com/dstein64/kmeans1d
Author: Daniel Steinberg
Author-email: ds@dannyadam.com
License: MIT
Keywords: k-means,machine learning,optimization
Classifier: Development Status :: 4 - Beta
Classifier: Intended Audience :: Developers
Classifier: Intended Audience :: Science/Research
Classifier: Topic :: Scientific/Engineering
Classifier: Topic :: Scientific/Engineering :: Artificial Intelligence
Classifier: Topic :: Scientific/Engineering :: Information Analysis
Classifier: Operating System :: Unix
Classifier: Operating System :: POSIX :: Linux
Classifier: Operating System :: MacOS
Classifier: Operating System :: Microsoft :: Windows
Classifier: Programming Language :: Python :: 3
Requires-Python: >=3.6
License-File: LICENSE
